oryx_wat_scraper/__init__.py
oryx_wat_scraper/async_client.py
oryx_wat_scraper/cli.py
oryx_wat_scraper/client.py
oryx_wat_scraper/exceptions.py
oryx_wat_scraper/models.py
oryx_wat_scraper-0.1.0.dist-info/METADATA
oryx_wat_scraper-0.1.0.dist-info/WHEEL
oryx_wat_scraper-0.1.0.dist-info/entry_points.txt
oryx_wat_scraper-0.1.0.dist-info/licenses/LICENSE
oryx_wat_scraper-0.1.0.dist-info/RECORD
